githammer/__init__.py
githammer/__main__.py
githammer/combinedcommit.py
githammer/config.py
githammer/countdict.py
githammer/dbtypes.py
githammer/frequency.py
githammer/hammer.py
githammer/summary/__init__.py
githammer/summary/graph.py
githammer/summary/table.py
git_hammer-0.3.2.dist-info/LICENSE
git_hammer-0.3.2.dist-info/METADATA
git_hammer-0.3.2.dist-info/WHEEL
git_hammer-0.3.2.dist-info/top_level.txt
git_hammer-0.3.2.dist-info/RECORD
