Metadata-Version: 2.1
Name: git-hammer
Version: 0.3.2
Summary: Statistics tool for git repositories
Home-page: https://github.com/asharov/git-hammer
Author: Jaakko Kangasharju
Author-email: ashar@iki.fi
License: UNKNOWN
Platform: UNKNOWN
Classifier: Programming Language :: Python :: 3
Classifier: License :: OSI Approved :: Apache Software License
Classifier: Development Status :: 3 - Alpha
Classifier: Operating System :: OS Independent
Requires-Python: >=3.7
Requires-Dist: gitpython
Requires-Dist: sqlalchemy (<2.0,>=1.4.7)
Requires-Dist: sqlalchemy-utils (>=0.37.0)
Requires-Dist: matplotlib (<3.1)
Requires-Dist: python-dateutil
Requires-Dist: globber
Requires-Dist: beautifultable
